azurefunctionhelpers/__init__.py
azurefunctionhelpers/observability/__init__.py
azurefunctionhelpers/observability/elastic_apm.py
azurefunctionhelpers/observability/generic.py
azurefunctionhelpers-0.1.9.dist-info/METADATA
azurefunctionhelpers-0.1.9.dist-info/WHEEL
azurefunctionhelpers-0.1.9.dist-info/top_level.txt
azurefunctionhelpers-0.1.9.dist-info/RECORD
