Metadata-Version: 2.1
Name: azurefunctionhelpers
Version: 0.1.9
Summary: Library of helpers for use with Azure Functions
Home-page: https://github.com/AirWalk-Digital/azure_function_helpers
Author: AirWalk Consulting
Author-email: info@airwalkconsulting.com
License: MIT
Platform: UNKNOWN
Requires-Dist: elastic-apm (==5.9.0)
